cryingonmykeyboard/__init__.py
cryingonmykeyboard/client.py
cryingonmykeyboard-0.1.1.dist-info/LICENSE
cryingonmykeyboard-0.1.1.dist-info/METADATA
cryingonmykeyboard-0.1.1.dist-info/WHEEL
cryingonmykeyboard-0.1.1.dist-info/top_level.txt
cryingonmykeyboard-0.1.1.dist-info/RECORD
