Metadata-Version: 2.1
Name: cryingonmykeyboard
Version: 0.1.1
Summary: Python client for Cryingonmykeyboard
Home-page: https://cryingonmykeyboard.com
Author: Devon Fulcher
Author-email: devonfulcher3@gmail.com
License: UNKNOWN
Project-URL: Bug Tracker, https://github.com/DevonFulcher/CryingOnMyKeyboard/issues
Platform: UNKNOWN
Classifier: Programming Language :: Python :: 3
Classifier: License :: OSI Approved :: MIT License
Classifier: Operating System :: OS Independent
Requires-Python: >=3.6
License-File: LICENSE
